{
    "res://scene/demo.tscn": {
        "type": "PackedScene",
        "ext": {},
        "sub": {
            "1": {
                "type": "CapsuleShape2D",
                "radius": 31.9656,
                "height": 76.9942
            }
        },
        "nodes": [
            {
                "type": "Node2D",
                "name": "demo"
            },
            {
                "type": "Node2D",
                "name": "ground",
                "parent": "."
            },
            {
                "type": "VectorGraphic",
                "name": "VectorGraphic",
                "parent": "ground",
                "position": {
                    "x": 160.57,
                    "y": 119.371
                },
                "shape": "@sub#1",
                "color": {
                    "r": 0.160784,
                    "g": 0.870588,
                    "b": 0.337255,
                    "a": 1
                }
            }
        ]
    }
}